LICENSE
README.md
setup.py
mlxu/__init__.py
mlxu/config.py
mlxu/jax_utils.py
mlxu/logging.py
mlxu/utils.py
mlxu.egg-info/PKG-INFO
mlxu.egg-info/SOURCES.txt
mlxu.egg-info/dependency_links.txt
mlxu.egg-info/requires.txt
mlxu.egg-info/top_level.txt